{
  "description": "This can be used as a unit of torque.",
  "SIUnit": "joule",
  "dimension": {"M": 1, "L": 2, "T": -2},

  "composites": ["Force * Length"],

  "convertibles": [
    {"target": "AbsoluteTemperature", "from": "joule", "to": "kelvin", "factor": "1 / Constants.BoltzmannConstant"},
    {"target": "Mass", "from": "joule", "to": "kilogram", "factor": "1 / (Constants.SpeedOfLight * Constants.SpeedOfLight)"}
  ],

  "units": [
    {"name": "joule", "symbol": "J", "scalePrefixes": true},
    {"name": "erg", "interval": "1e-7"},
    {"name": "electronvolt", "symbol": "eV", "interval": "Constants.ElementaryCharge", "scalePrefixes": true, "notExact": true},
    {"name": "rydberg", "symbol": "Ry", "interval": "13.6056925330", "baseUnit": "electronvolt", "notExact": true},
    {"name": "atomic unit of energy", "symbol": "E_h", "interval": "2", "baseUnit": "rydberg", "notExact": true},

    {"name": "calorie", "symbol": "cal", "aliases": ["cal_IT"], "baseUnit": "calorie(IT)",
      "attributes": [
        {"name": "IT", "interval": "4.1868"}
      ]
    }
  ]
}